flake8_postponed_annotations/__init__.py
flake8_postponed_annotations-1.3.0.dist-info/METADATA
flake8_postponed_annotations-1.3.0.dist-info/WHEEL
flake8_postponed_annotations-1.3.0.dist-info/top_level.txt
flake8_postponed_annotations-1.3.0.dist-info/RECORD
