Metadata-Version: 2.1
Name: flake8-postponed-annotations
Version: 1.3.0
Summary: Flake8 postponed annotations validation
Home-page: https://github.com/plinss/flake8-postponed-annotations/
Author: Peter Linss
Author-email: pypi@linss.com
License: UNKNOWN
Platform: UNKNOWN
Classifier: Framework :: Flake8
Classifier: Environment :: Console
Classifier: Intended Audience :: Developers
Classifier: License :: OSI Approved :: GNU Lesser General Public License v3 or later (LGPLv3+)
Classifier: Programming Language :: Python
Classifier: Programming Language :: Python :: 3
Classifier: Programming Language :: Python :: 3.7
Classifier: Programming Language :: Python :: 3.8
Classifier: Programming Language :: Python :: 3.9
Classifier: Programming Language :: Python :: 3.10
Classifier: Topic :: Software Development :: Libraries :: Python Modules
Classifier: Topic :: Software Development :: Quality Assurance
Requires-Python: >=3.7
Requires-Dist: flake8-modern-annotations
